scaffold_fastapi/__init__.py
scaffold_fastapi/cli.py
scaffold_fastapi/generators/__init__.py
scaffold_fastapi/generators/app.py
scaffold_fastapi/generators/celery.py
scaffold_fastapi/generators/docker.py
scaffold_fastapi/generators/env.py
scaffold_fastapi/generators/terraform.py
scaffold_fastapi-0.1.7.dist-info/METADATA
scaffold_fastapi-0.1.7.dist-info/WHEEL
scaffold_fastapi-0.1.7.dist-info/entry_points.txt
scaffold_fastapi-0.1.7.dist-info/licenses/LICENSE
scaffold_fastapi-0.1.7.dist-info/RECORD
